cionuke/VERSION
cionuke/__about__.py
cionuke/__init__.py
cionuke/conductor_menu.py
cionuke/connect.py
cionuke/const.py
cionuke/entry.py
cionuke/post_install.py
cionuke/submit.py
cionuke/utils.py
cionuke/validation.py
cionuke/components/__init__.py
cionuke/components/actions.py
cionuke/components/advanced.py
cionuke/components/assets.py
cionuke/components/autosave.py
cionuke/components/conductor_knob.py
cionuke/components/environment.py
cionuke/components/frames.py
cionuke/components/instance_type.py
cionuke/components/metadata.py
cionuke/components/preview.py
cionuke/components/project.py
cionuke/components/software.py
cionuke/components/title.py
cionuke/icons/ConductorConnect_18x18.png
cionuke/icons/ConductorConnect_24x24.png
cionuke/icons/ConductorConnect_36x36.png
cionuke/icons/ConductorConnect_48x48.png
cionuke/icons/ConductorError_18x18.png
cionuke/icons/ConductorError_24x24.png
cionuke/icons/ConductorError_36x36.png
cionuke/icons/ConductorError_48x48.png
cionuke/icons/ConductorInfo_18x18.png
cionuke/icons/ConductorInfo_24x24.png
cionuke/icons/ConductorInfo_36x36.png
cionuke/icons/ConductorInfo_48x48.png
cionuke/icons/ConductorShow_18x18.png
cionuke/icons/ConductorShow_24x24.png
cionuke/icons/ConductorShow_36x36.png
cionuke/icons/ConductorShow_48x48.png
cionuke/icons/ConductorSubmit_18x18.png
cionuke/icons/ConductorSubmit_24x24.png
cionuke/icons/ConductorSubmit_36x36.png
cionuke/icons/ConductorSubmit_48x48.png
cionuke/icons/ConductorSuccess_18x18.png
cionuke/icons/ConductorSuccess_24x24.png
cionuke/icons/ConductorSuccess_36x36.png
cionuke/icons/ConductorSuccess_48x48.png
cionuke/icons/ConductorWarning_18x18.png
cionuke/icons/ConductorWarning_24x24.png
cionuke/icons/ConductorWarning_36x36.png
cionuke/icons/ConductorWarning_48x48.png
cionuke/widgets/__init__.py
cionuke/widgets/buttoned_scroll_dialog.py
cionuke/widgets/key_value_grp.py
cionuke/widgets/notice_grp.py
cionuke-0.8.2.data/data/nuke/menu.py
cionuke-0.8.2.dist-info/METADATA
cionuke-0.8.2.dist-info/WHEEL
cionuke-0.8.2.dist-info/top_level.txt
cionuke-0.8.2.dist-info/RECORD
