Metadata-Version: 2.4
Name: cionuke
Version: 0.8.2
Summary: Nuke plugin for Conductor Cloud Rendering Platform.
Home-page: https://github.com/ConductorTechnologies/cionuke
Author: conductor
Author-email: info@conductortech.com
Classifier: Operating System :: OS Independent
Classifier: Programming Language :: Python
Classifier: Topic :: Multimedia :: Graphics :: 3D Rendering
Requires-Dist: ciocore<10.0.0,>=9.0.0
Requires-Dist: ciopath<2.0.0,>=1.1.2
Requires-Dist: cioseq<1.0.0,>=0.5.0
Requires-Dist: ciotemplate<1.0.0,>=0.1.2
Dynamic: author
Dynamic: author-email
Dynamic: classifier
Dynamic: description
Dynamic: description-content-type
Dynamic: home-page
Dynamic: requires-dist
Dynamic: summary
